finance_trader/__init__.py
finance_trader-1.0.0.dev1.dist-info/METADATA
finance_trader-1.0.0.dev1.dist-info/WHEEL
finance_trader-1.0.0.dev1.dist-info/top_level.txt
finance_trader-1.0.0.dev1.dist-info/RECORD
