Metadata-Version: 2.1
Name: finance-trader
Version: 1.0.0.dev1
Summary: finance_trader
Home-page: https://github.com/pyted/finance_trader
Author: pyted
Author-email: pyted@outlook.com
License: MIT
Classifier: License :: OSI Approved :: MIT License
Classifier: Programming Language :: Python
Classifier: Programming Language :: Python :: 3
Classifier: Programming Language :: Python :: 3.6
Classifier: Programming Language :: Python :: Implementation :: CPython
Classifier: Programming Language :: Python :: Implementation :: PyPy
Requires-Python: >=3.6.0
